[{"model": "admin.logentry", "pk": 1, "fields": {"action_time": "2024-02-10T04:00:20.168Z", "user": 1, "content_type": 9, "object_id": "4", "object_repr": "Category object (4)", "action_flag": 1, "change_message": "[{\"added\": {}}]"}}, {"model": "admin.logentry", "pk": 2, "fields": {"action_time": "2024-02-10T04:00:26.321Z", "user": 1, "content_type": 9, "object_id": "5", "object_repr": "Category object (5)", "action_flag": 1, "change_message": "[{\"added\": {}}]"}}, {"model": "admin.logentry", "pk": 3, "fields": {"action_time": "2024-02-10T04:04:02.196Z", "user": 1, "content_type": 7, "object_id": "1", "object_repr": "Portfolio object (1)", "action_flag": 2, "change_message": "[{\"changed\": {\"fields\": [\"Title\", \"Description\"]}}]"}}, {"model": "admin.logentry", "pk": 4, "fields": {"action_time": "2024-02-10T04:04:48.050Z", "user": 1, "content_type": 7, "object_id": "2", "object_repr": "Portfolio object (2)", "action_flag": 1, "change_message": "[{\"added\": {}}]"}}, {"model": "admin.logentry", "pk": 5, "fields": {"action_time": "2024-02-10T04:05:05.102Z", "user": 1, "content_type": 8, "object_id": "3", "object_repr": "Place object (3)", "action_flag": 3, "change_message": ""}}, {"model": "admin.logentry", "pk": 6, "fields": {"action_time": "2024-02-10T04:05:06.127Z", "user": 1, "content_type": 8, "object_id": "2", "object_repr": "Place object (2)", "action_flag": 3, "change_message": ""}}, {"model": "admin.logentry", "pk": 7, "fields": {"action_time": "2024-02-10T04:05:06.196Z", "user": 1, "content_type": 8, "object_id": "1", "object_repr": "Place object (1)", "action_flag": 3, "change_message": ""}}, {"model": "admin.logentry", "pk": 8, "fields": {"action_time": "2024-02-10T04:08:40.700Z", "user": 1, "content_type": 8, "object_id": "4", "object_repr": "Place object (4)", "action_flag": 1, "change_message": "[{\"added\": {}}]"}}, {"model": "admin.logentry", "pk": 9, "fields": {"action_time": "2024-02-10T04:09:06.291Z", "user": 1, "content_type": 9, "object_id": "3", "object_repr": "Category object (3)", "action_flag": 3, "change_message": ""}}, {"model": "admin.logentry", "pk": 10, "fields": {"action_time": "2024-02-10T04:09:06.492Z", "user": 1, "content_type": 9, "object_id": "2", "object_repr": "Category object (2)", "action_flag": 3, "change_message": ""}}, {"model": "admin.logentry", "pk": 11, "fields": {"action_time": "2024-02-10T04:09:06.659Z", "user": 1, "content_type": 9, "object_id": "1", "object_repr": "Category object (1)", "action_flag": 3, "change_message": ""}}, {"model": "admin.logentry", "pk": 12, "fields": {"action_time": "2024-02-10T04:09:20.893Z", "user": 1, "content_type": 8, "object_id": "4", "object_repr": "Place object (4)", "action_flag": 2, "change_message": "[{\"changed\": {\"fields\": [\"\\u041a\\u0430\\u0442\\u0435\\u0433\\u043e\\u0440\\u0438\\u0438\"]}}]"}}, {"model": "admin.logentry", "pk": 13, "fields": {"action_time": "2024-02-10T04:11:41.755Z", "user": 1, "content_type": 8, "object_id": "5", "object_repr": "Place object (5)", "action_flag": 1, "change_message": "[{\"added\": {}}]"}}, {"model": "admin.logentry", "pk": 14, "fields": {"action_time": "2024-02-25T03:18:16.162Z", "user": 1, "content_type": 8, "object_id": "4", "object_repr": "Place object (4)", "action_flag": 2, "change_message": "[{\"changed\": {\"fields\": [\"\\u041c\\u0435\\u0441\\u0442\\u043e \\u0440\\u0430\\u0431\\u043e\\u0442\\u044b\", \"\\u0414\\u043e\\u043b\\u0436\\u043d\\u043e\\u0441\\u0442\\u044c\", \"Years\", \"\\u041e\\u0431\\u044f\\u0437\\u0430\\u043d\\u043d\\u043e\\u0441\\u0442\\u0438\", \"\\u0414\\u043e\\u0441\\u0442\\u0438\\u0436\\u0435\\u043d\\u0438\\u044f\", \"\\u041d\\u0430\\u0447\\u0430\\u043b\\u043e \\u0440\\u0430\\u0431\\u043e\\u0442\\u044b\", \"\\u041a\\u043e\\u043d\\u0435\\u0446 \\u0440\\u0430\\u0431\\u043e\\u0442\\u044b\"]}}]"}}, {"model": "admin.logentry", "pk": 15, "fields": {"action_time": "2024-02-25T03:34:31.075Z", "user": 1, "content_type": 8, "object_id": "5", "object_repr": "Place object (5)", "action_flag": 2, "change_message": "[{\"changed\": {\"fields\": [\"\\u041c\\u0435\\u0441\\u0442\\u043e \\u0440\\u0430\\u0431\\u043e\\u0442\\u044b\", \"\\u0414\\u043e\\u043b\\u0436\\u043d\\u043e\\u0441\\u0442\\u044c\", \"Years\", \"\\u041e\\u0431\\u044f\\u0437\\u0430\\u043d\\u043d\\u043e\\u0441\\u0442\\u0438\", \"\\u0414\\u043e\\u0441\\u0442\\u0438\\u0436\\u0435\\u043d\\u0438\\u044f\", \"\\u041d\\u0430\\u0447\\u0430\\u043b\\u043e \\u0440\\u0430\\u0431\\u043e\\u0442\\u044b\", \"\\u041a\\u043e\\u043d\\u0435\\u0446 \\u0440\\u0430\\u0431\\u043e\\u0442\\u044b\"]}}]"}}, {"model": "admin.logentry", "pk": 16, "fields": {"action_time": "2024-02-25T03:35:01.174Z", "user": 1, "content_type": 8, "object_id": "5", "object_repr": "Place object (5)", "action_flag": 2, "change_message": "[{\"changed\": {\"fields\": [\"\\u041e\\u0431\\u044f\\u0437\\u0430\\u043d\\u043d\\u043e\\u0441\\u0442\\u0438\", \"\\u0414\\u043e\\u0441\\u0442\\u0438\\u0436\\u0435\\u043d\\u0438\\u044f\"]}}]"}}, {"model": "admin.logentry", "pk": 17, "fields": {"action_time": "2024-02-25T03:35:23.179Z", "user": 1, "content_type": 8, "object_id": "4", "object_repr": "Place object (4)", "action_flag": 2, "change_message": "[{\"changed\": {\"fields\": [\"\\u041e\\u0431\\u044f\\u0437\\u0430\\u043d\\u043d\\u043e\\u0441\\u0442\\u0438\", \"\\u0414\\u043e\\u0441\\u0442\\u0438\\u0436\\u0435\\u043d\\u0438\\u044f\"]}}]"}}, {"model": "admin.logentry", "pk": 18, "fields": {"action_time": "2024-02-25T03:35:30.567Z", "user": 1, "content_type": 8, "object_id": "5", "object_repr": "Place object (5)", "action_flag": 2, "change_message": "[{\"changed\": {\"fields\": [\"\\u041e\\u0431\\u044f\\u0437\\u0430\\u043d\\u043d\\u043e\\u0441\\u0442\\u0438\", \"\\u0414\\u043e\\u0441\\u0442\\u0438\\u0436\\u0435\\u043d\\u0438\\u044f\"]}}]"}}, {"model": "admin.logentry", "pk": 19, "fields": {"action_time": "2024-02-25T03:36:40.317Z", "user": 1, "content_type": 8, "object_id": "5", "object_repr": "Place object (5)", "action_flag": 2, "change_message": "[{\"changed\": {\"fields\": [\"\\u0414\\u043e\\u043b\\u0436\\u043d\\u043e\\u0441\\u0442\\u044c\"]}}]"}}, {"model": "admin.logentry", "pk": 20, "fields": {"action_time": "2024-02-25T03:40:25.923Z", "user": 1, "content_type": 8, "object_id": "6", "object_repr": "Place object (6)", "action_flag": 1, "change_message": "[{\"added\": {}}]"}}, {"model": "admin.logentry", "pk": 21, "fields": {"action_time": "2024-02-25T03:44:02.811Z", "user": 1, "content_type": 8, "object_id": "7", "object_repr": "Place object (7)", "action_flag": 1, "change_message": "[{\"added\": {}}]"}}, {"model": "admin.logentry", "pk": 22, "fields": {"action_time": "2024-02-25T03:55:15.491Z", "user": 1, "content_type": 8, "object_id": "8", "object_repr": "Place object (8)", "action_flag": 1, "change_message": "[{\"added\": {}}]"}}, {"model": "admin.logentry", "pk": 23, "fields": {"action_time": "2024-02-25T04:43:54.619Z", "user": 1, "content_type": 8, "object_id": "8", "object_repr": "Place object (8)", "action_flag": 2, "change_message": "[{\"changed\": {\"fields\": [\"\\u041e\\u0431\\u044f\\u0437\\u0430\\u043d\\u043d\\u043e\\u0441\\u0442\\u0438\", \"\\u0414\\u043e\\u0441\\u0442\\u0438\\u0436\\u0435\\u043d\\u0438\\u044f\", \"Ordinal\"]}}]"}}, {"model": "admin.logentry", "pk": 24, "fields": {"action_time": "2024-02-25T04:44:06.120Z", "user": 1, "content_type": 8, "object_id": "7", "object_repr": "Place object (7)", "action_flag": 2, "change_message": "[{\"changed\": {\"fields\": [\"\\u041e\\u0431\\u044f\\u0437\\u0430\\u043d\\u043d\\u043e\\u0441\\u0442\\u0438\"]}}]"}}, {"model": "admin.logentry", "pk": 25, "fields": {"action_time": "2024-02-25T04:44:48.553Z", "user": 1, "content_type": 8, "object_id": "6", "object_repr": "Place object (6)", "action_flag": 2, "change_message": "[{\"changed\": {\"fields\": [\"\\u041e\\u0431\\u044f\\u0437\\u0430\\u043d\\u043d\\u043e\\u0441\\u0442\\u0438\", \"\\u041a\\u0430\\u0442\\u0435\\u0433\\u043e\\u0440\\u0438\\u0438\"]}}]"}}, {"model": "admin.logentry", "pk": 26, "fields": {"action_time": "2024-02-25T04:45:14.121Z", "user": 1, "content_type": 8, "object_id": "5", "object_repr": "Place object (5)", "action_flag": 2, "change_message": "[{\"changed\": {\"fields\": [\"\\u041e\\u0431\\u044f\\u0437\\u0430\\u043d\\u043d\\u043e\\u0441\\u0442\\u0438\"]}}]"}}, {"model": "admin.logentry", "pk": 27, "fields": {"action_time": "2024-02-25T04:45:41.311Z", "user": 1, "content_type": 8, "object_id": "4", "object_repr": "Place object (4)", "action_flag": 2, "change_message": "[{\"changed\": {\"fields\": [\"\\u041e\\u0431\\u044f\\u0437\\u0430\\u043d\\u043d\\u043e\\u0441\\u0442\\u0438\", \"\\u041a\\u0430\\u0442\\u0435\\u0433\\u043e\\u0440\\u0438\\u0438\"]}}]"}}, {"model": "admin.logentry", "pk": 28, "fields": {"action_time": "2024-02-25T04:48:32.751Z", "user": 1, "content_type": 8, "object_id": "9", "object_repr": "Place object (9)", "action_flag": 1, "change_message": "[{\"added\": {}}]"}}, {"model": "admin.logentry", "pk": 29, "fields": {"action_time": "2024-02-25T04:57:04.339Z", "user": 1, "content_type": 8, "object_id": "10", "object_repr": "Place object (10)", "action_flag": 1, "change_message": "[{\"added\": {}}]"}}, {"model": "admin.logentry", "pk": 30, "fields": {"action_time": "2024-02-25T04:57:27.881Z", "user": 1, "content_type": 8, "object_id": "10", "object_repr": "Place object (10)", "action_flag": 2, "change_message": "[{\"changed\": {\"fields\": [\"\\u041a\\u0430\\u0442\\u0435\\u0433\\u043e\\u0440\\u0438\\u0438\"]}}]"}}, {"model": "admin.logentry", "pk": 31, "fields": {"action_time": "2024-02-25T04:58:53.595Z", "user": 1, "content_type": 8, "object_id": "11", "object_repr": "Place object (11)", "action_flag": 1, "change_message": "[{\"added\": {}}]"}}, {"model": "admin.logentry", "pk": 32, "fields": {"action_time": "2024-02-25T05:38:23.987Z", "user": 1, "content_type": 7, "object_id": "1", "object_repr": "Portfolio object (1)", "action_flag": 2, "change_message": "[{\"changed\": {\"fields\": [\"\\u0421\\u0442\\u0430\\u0442\\u044c\\u044f\", \"\\u0414\\u043e\\u0441\\u0442\\u0438\\u0436\\u0435\\u043d\\u0438\\u0435\"]}}]"}}, {"model": "admin.logentry", "pk": 33, "fields": {"action_time": "2024-02-25T05:45:28.449Z", "user": 1, "content_type": 7, "object_id": "1", "object_repr": "Portfolio object (1)", "action_flag": 2, "change_message": "[{\"changed\": {\"fields\": [\"Url\"]}}]"}}, {"model": "admin.logentry", "pk": 34, "fields": {"action_time": "2024-02-25T05:46:06.256Z", "user": 1, "content_type": 7, "object_id": "1", "object_repr": "Portfolio object (1)", "action_flag": 2, "change_message": "[{\"changed\": {\"fields\": [\"Url\"]}}]"}}, {"model": "admin.logentry", "pk": 35, "fields": {"action_time": "2024-02-25T05:56:47.156Z", "user": 1, "content_type": 7, "object_id": "2", "object_repr": "Portfolio object (2)", "action_flag": 2, "change_message": "[{\"changed\": {\"fields\": [\"\\u0421\\u0442\\u0430\\u0442\\u044c\\u044f\", \"\\u0414\\u043e\\u0441\\u0442\\u0438\\u0436\\u0435\\u043d\\u0438\\u0435\"]}}]"}}, {"model": "auth.permission", "pk": 1, "fields": {"name": "Can add log entry", "content_type": 1, "codename": "add_logentry"}}, {"model": "auth.permission", "pk": 2, "fields": {"name": "Can change log entry", "content_type": 1, "codename": "change_logentry"}}, {"model": "auth.permission", "pk": 3, "fields": {"name": "Can delete log entry", "content_type": 1, "codename": "delete_logentry"}}, {"model": "auth.permission", "pk": 4, "fields": {"name": "Can view log entry", "content_type": 1, "codename": "view_logentry"}}, {"model": "auth.permission", "pk": 5, "fields": {"name": "Can add permission", "content_type": 2, "codename": "add_permission"}}, {"model": "auth.permission", "pk": 6, "fields": {"name": "Can change permission", "content_type": 2, "codename": "change_permission"}}, {"model": "auth.permission", "pk": 7, "fields": {"name": "Can delete permission", "content_type": 2, "codename": "delete_permission"}}, {"model": "auth.permission", "pk": 8, "fields": {"name": "Can view permission", "content_type": 2, "codename": "view_permission"}}, {"model": "auth.permission", "pk": 9, "fields": {"name": "Can add group", "content_type": 3, "codename": "add_group"}}, {"model": "auth.permission", "pk": 10, "fields": {"name": "Can change group", "content_type": 3, "codename": "change_group"}}, {"model": "auth.permission", "pk": 11, "fields": {"name": "Can delete group", "content_type": 3, "codename": "delete_group"}}, {"model": "auth.permission", "pk": 12, "fields": {"name": "Can view group", "content_type": 3, "codename": "view_group"}}, {"model": "auth.permission", "pk": 13, "fields": {"name": "Can add user", "content_type": 4, "codename": "add_user"}}, {"model": "auth.permission", "pk": 14, "fields": {"name": "Can change user", "content_type": 4, "codename": "change_user"}}, {"model": "auth.permission", "pk": 15, "fields": {"name": "Can delete user", "content_type": 4, "codename": "delete_user"}}, {"model": "auth.permission", "pk": 16, "fields": {"name": "Can view user", "content_type": 4, "codename": "view_user"}}, {"model": "auth.permission", "pk": 17, "fields": {"name": "Can add content type", "content_type": 5, "codename": "add_contenttype"}}, {"model": "auth.permission", "pk": 18, "fields": {"name": "Can change content type", "content_type": 5, "codename": "change_contenttype"}}, {"model": "auth.permission", "pk": 19, "fields": {"name": "Can delete content type", "content_type": 5, "codename": "delete_contenttype"}}, {"model": "auth.permission", "pk": 20, "fields": {"name": "Can view content type", "content_type": 5, "codename": "view_contenttype"}}, {"model": "auth.permission", "pk": 21, "fields": {"name": "Can add session", "content_type": 6, "codename": "add_session"}}, {"model": "auth.permission", "pk": 22, "fields": {"name": "Can change session", "content_type": 6, "codename": "change_session"}}, {"model": "auth.permission", "pk": 23, "fields": {"name": "Can delete session", "content_type": 6, "codename": "delete_session"}}, {"model": "auth.permission", "pk": 24, "fields": {"name": "Can view session", "content_type": 6, "codename": "view_session"}}, {"model": "auth.permission", "pk": 25, "fields": {"name": "Can add portfolio", "content_type": 7, "codename": "add_portfolio"}}, {"model": "auth.permission", "pk": 26, "fields": {"name": "Can change portfolio", "content_type": 7, "codename": "change_portfolio"}}, {"model": "auth.permission", "pk": 27, "fields": {"name": "Can delete portfolio", "content_type": 7, "codename": "delete_portfolio"}}, {"model": "auth.permission", "pk": 28, "fields": {"name": "Can view portfolio", "content_type": 7, "codename": "view_portfolio"}}, {"model": "auth.permission", "pk": 29, "fields": {"name": "Can add place", "content_type": 8, "codename": "add_place"}}, {"model": "auth.permission", "pk": 30, "fields": {"name": "Can change place", "content_type": 8, "codename": "change_place"}}, {"model": "auth.permission", "pk": 31, "fields": {"name": "Can delete place", "content_type": 8, "codename": "delete_place"}}, {"model": "auth.permission", "pk": 32, "fields": {"name": "Can view place", "content_type": 8, "codename": "view_place"}}, {"model": "auth.permission", "pk": 33, "fields": {"name": "Can add category", "content_type": 9, "codename": "add_category"}}, {"model": "auth.permission", "pk": 34, "fields": {"name": "Can change category", "content_type": 9, "codename": "change_category"}}, {"model": "auth.permission", "pk": 35, "fields": {"name": "Can delete category", "content_type": 9, "codename": "delete_category"}}, {"model": "auth.permission", "pk": 36, "fields": {"name": "Can view category", "content_type": 9, "codename": "view_category"}}, {"model": "auth.user", "pk": 1, "fields": {"password": "pbkdf2_sha256$720000$QFUlyl0aCxIDtZ45DWgtTV$GeDp+xoOwhgzA2CLEKLcaYcHLFu5bzgohWOzWr6Iq14=", "last_login": "2024-02-25T02:29:25.538Z", "is_superuser": true, "username": "Dato", "first_name": "", "last_name": "", "email": "dato138it@gyandex.ru", "is_staff": true, "is_active": true, "date_joined": "2024-02-04T09:58:48.368Z", "groups": [], "user_permissions": []}}, {"model": "contenttypes.contenttype", "pk": 1, "fields": {"app_label": "admin", "model": "logentry"}}, {"model": "contenttypes.contenttype", "pk": 2, "fields": {"app_label": "auth", "model": "permission"}}, {"model": "contenttypes.contenttype", "pk": 3, "fields": {"app_label": "auth", "model": "group"}}, {"model": "contenttypes.contenttype", "pk": 4, "fields": {"app_label": "auth", "model": "user"}}, {"model": "contenttypes.contenttype", "pk": 5, "fields": {"app_label": "contenttypes", "model": "contenttype"}}, {"model": "contenttypes.contenttype", "pk": 6, "fields": {"app_label": "sessions", "model": "session"}}, {"model": "contenttypes.contenttype", "pk": 7, "fields": {"app_label": "portfolio", "model": "portfolio"}}, {"model": "contenttypes.contenttype", "pk": 8, "fields": {"app_label": "portfolio", "model": "place"}}, {"model": "contenttypes.contenttype", "pk": 9, "fields": {"app_label": "portfolio", "model": "category"}}, {"model": "sessions.session", "pk": "lqeqmkfybncby3ep9smum1gu44cklg12", "fields": {"session_data": ".eJxVjDsOwjAQBe_iGln-xR9Kes5g2bteHEC2FCcV4u4QKQW0b2bei8W0rTVuoyxxRnZmkp1-t5zgUdoO8J7arXPobV3mzHeFH3Twa8fyvBzu30FNo35rpwtQIeOsJpAWrcAksxMkUCmfwEo0WhujjaQgLanJ60BO-WAnBT6z9wfm-DdN:1rXKTC:_v_Q-PHN0IlJqJFyy4ArVaIFNZxm2BnRy364hNBkLGg", "expire_date": "2024-02-20T12:22:34.500Z"}}, {"model": "sessions.session", "pk": "vs5pk439bwsncz8s26js9lvrksntn90r", "fields": {"session_data": ".eJxVjDsOwjAQBe_iGln-xR9Kes5g2bteHEC2FCcV4u4QKQW0b2bei8W0rTVuoyxxRnZmkp1-t5zgUdoO8J7arXPobV3mzHeFH3Twa8fyvBzu30FNo35rpwtQIeOsJpAWrcAksxMkUCmfwEo0WhujjaQgLanJ60BO-WAnBT6z9wfm-DdN:1re4Gb:TQshzn0mox_F2ujp296oyqMPHI8Sb9e8aVZNUHKRaWE", "expire_date": "2024-03-10T02:29:25.544Z"}}, {"model": "portfolio.place", "pk": 4, "fields": {"title": "Иркутский государственный университет, Иркутск", "spec": "Информационные технологии и телекоммуникационные системы (Квалификация бакалавр)", "years": "4", "description": "Skills: Html, Css, Timeweb, Linux, Qemu-kvm, Ssh, Lamp, Phpmyadmin, Mysql, Php;", "progress": "Для разработки своего сайта, куда публиковал все решенные мной интересные задачи, отчеты лабораторных работ и презентации, сверстал простой сайт, развернул в Qemu-kvm виртуальную машину с операционной системой Ubuntu, в котором установил и настроил веб-сервер Lamp с своей базой данных на Mysql, опубликовал сайт в сервис Timeweb и в нем разрегистрировал домен;", "doc": "uploads/2024/02/10/test_za2Mj3P.jpg", "begin": "2011-09-01", "finish": "2015-05-31", "is_published": true, "cat": 5, "ordinal": 1}}, {"model": "portfolio.place", "pk": 5, "fields": {"title": "Иркутский государственный университет, Иркутск", "spec": "Информационные технологии и телекоммуникационные системы (Квалификация бакалавр)", "years": "4", "description": "Skills: Html, Css, Timeweb, Linux, Qemu-kvm, Ssh, Lamp, Phpmyadmin, Mysql, Php;", "progress": "Для защиты лабораторных работ по дисциплине Локально-вычислительные сети в виртуальной машине Ubuntu настроил программу для проектирования сетей Packet Tracer, спроектрировал лабораторные работы по темам \"Использование DHCP-протокола через маршрутизатор и через сервер\", \"Wi-Fi - беспроводная передача данных\", а также по теме \"Локальная сеть\" развернул виртуальные машины в Virtualbox две операционные системы Windows 10 и Windows Server 2012 для настройки локальной сети. В Windows Server установил DHCP и DNS сервера и добавил в домен клиентского компьютера Windows 10;", "doc": "uploads/2024/02/10/test_SGH0DTA.jpg", "begin": "2011-09-01", "finish": "2015-05-31", "is_published": true, "cat": 4, "ordinal": 2}}, {"model": "portfolio.place", "pk": 6, "fields": {"title": "Иркутский государственный университет, Иркутск", "spec": "Электроника и наноэлектроника (Квалификация магистр)", "years": "2", "description": "Спутниковые радионавигационные системы (СРНС), Rinex, Одночастотные приемники СРНС, Borland C++ Builder, C++;", "progress": "Для защиты диссертации по теме \"Использование данных с одночастотных приемников спутниковых радионавигационных систем для коррекции модели ионосферы\" освоил технологию приёма получения данных с одночастотных приемников спутниковых радионавигационных систем, получил данные, разработал программу на C++, которая обрабатывает и сортирует данные двух координат из файла по столбцам, рисует график, чтобы увидеть желаемый результат в точности определения координат спутников, рассмотрел способы уменьшения ошибок измерения псевдодальности и показал, что из-за нестабильности аппаратуры потребителя информация о состоянии ионосферы может быть получена в каждый момент времени по разностям ПД двух навигационных спутников;", "doc": "uploads/2024/02/25/test.jpg", "begin": "2015-09-01", "finish": "2017-05-31", "is_published": true, "cat": 5, "ordinal": 3}}, {"model": "portfolio.place", "pk": 7, "fields": {"title": "Иркутский государственный университет, Иркутск", "spec": "Информационная безопасность (Дополнительное образование)", "years": "1", "description": "Skills: Qemu-Kvm, Virtualbox, Linux, Ssh, Iptables, Nmap, Bash, Vsftpd, Telnet, Nginx, Squid, Tcpdump, Icmp, Tripwire, Rkhunter, Crontab;", "progress": "Для защиты выпускной квалификационной работы по теме \"Утилита для сканирования безопасности сети Nmap\" проанализировал состояние виртуальных машин в Qemu-Kvm инструментом Nmap. Дополнительно для перехвата трафиков использовал Tcpdump. Для того чтобы обезопасить свои системы, настроил правила в Iptables и развернул антируткит, который по определенному раписанию выгружал отчет о состоянии системы;", "doc": "uploads/2024/02/25/test_kSwYJo3.jpg", "begin": "2017-09-01", "finish": "2018-05-31", "is_published": true, "cat": 4, "ordinal": 4}}, {"model": "portfolio.place", "pk": 8, "fields": {"title": "Всероссийский государственный университет юстиции (РПА Минюста России), Иркутск", "spec": "Technical Specialist", "years": "5", "description": "Обязанности: работа с сайтами, поддержка функционирования серверов, в том числе с использованием сред виртуализации, восстановление работоспособности ПК, периферийных устройств, оборудования видеоконференцсвязи, аудио-видеофиксации, локальной сети при сбоях или выходе из строя сетевого оборудования, техническая поддержка пользователей, разрабатывать решения, которые упростят эксплуатацию и автоматизируют рутину, поддержка функционирования сервисов СУБД; Skills: Python, Html, Wordpress, Bash;", "progress": "Разработал программы, которые анализируют, обрабатывают и сортируют код на сайте организации. Это позволило мне ускорить процесс корректировки тегов на сайте по запросу Россобрнадзор;", "doc": "", "begin": "2018-03-01", "finish": "2022-11-01", "is_published": true, "cat": 4, "ordinal": 5}}, {"model": "portfolio.place", "pk": 9, "fields": {"title": "Всероссийский государственный университет юстиции (РПА Минюста России), Иркутск", "spec": "Technical Specialist", "years": "5", "description": "Обязанности: работа с сайтами, поддержка функционирования серверов, в том числе с использованием сред виртуализации, восстановление работоспособности ПК, периферийных устройств, оборудования видеоконференцсвязи, аудио-видеофиксации, локальной сети при сбоях или выходе из строя сетевого оборудования, техническая поддержка пользователей, разрабатывать решения, которые упростят эксплуатацию и автоматизируют рутину, поддержка функционирования сервисов СУБД; Skills: Python, Html, Wordpress, Bash;", "progress": "Для импортозамещения с Windows на Redos, развернул виртуальную тестовую машину Redos в Hyber-v, в котором развернул Pxe сервер для развертывания Redos с загрузкой в Uefi по сети. Это сэкономило время на внедрение системы Redos в компьютерных классах;", "doc": "", "begin": "2018-03-01", "finish": "2022-11-01", "is_published": true, "cat": 4, "ordinal": 6}}, {"model": "portfolio.place", "pk": 10, "fields": {"title": "Всероссийский государственный университет юстиции (РПА Минюста России), Иркутск", "spec": "Technical Specialist", "years": "5", "description": "Обязанности: работа с сайтами, поддержка функционирования серверов, в том числе с использованием сред виртуализации, восстановление работоспособности ПК, периферийных устройств, оборудования видеоконференцсвязи, аудио-видеофиксации, локальной сети при сбоях или выходе из строя сетевого оборудования, техническая поддержка пользователей, разрабатывать решения, которые упростят эксплуатацию и автоматизируют рутину, поддержка функционирования сервисов СУБД; Skills: Python, Html, Wordpress, Bash;", "progress": "Развернул виртуальный сервер в Altlinux и разработал в нем базу \"Инвентаризация компьютерной техники в здании\". Это позволило мне быстро предоставлять отчеты об оборудовании в здании;", "doc": "", "begin": "2018-03-01", "finish": "2022-11-01", "is_published": true, "cat": 5, "ordinal": 7}}, {"model": "portfolio.place", "pk": 11, "fields": {"title": "Всероссийский государственный университет юстиции (РПА Минюста России), Иркутск", "spec": "Technical Specialist", "years": "5", "description": "Обязанности: работа с сайтами, поддержка функционирования серверов, в том числе с использованием сред виртуализации, восстановление работоспособности ПК, периферийных устройств, оборудования видеоконференцсвязи, аудио-видеофиксации, локальной сети при сбоях или выходе из строя сетевого оборудования, техническая поддержка пользователей, разрабатывать решения, которые упростят эксплуатацию и автоматизируют рутину, поддержка функционирования сервисов СУБД; Skills: Python, Html, Wordpress, Bash;", "progress": "Разработал скрипты на языках Bash и Python для автоматизации работы в компьютерных классах и аудиториях;", "doc": "", "begin": "2018-03-01", "finish": "2022-11-01", "is_published": true, "cat": 5, "ordinal": 8}}, {"model": "portfolio.portfolio", "pk": 1, "fields": {"title": "Для разработки своего сайта, куда публиковал все решенные мной интересные задачи, отчеты лабораторных работ и презентации, сверстал простой сайт, развернул в Qemu-kvm виртуальную машину с операционной системой Ubuntu, в котором установил и настроил веб-сервер Lamp с своей базой данных на Mysql, опубликовал сайт в сервис Timeweb и в нем разрегистрировал домен", "description": "Decision:\r\n$ wget https://ubuntu.com/download/desktop/thank-you?version=22.04.3&architecture=amd64\r\n$ sudo dnf install https://kojihub.stream.centos.org/kojifiles/packages/libvirt-python/8.5.0/2.el9/x86_64/\r\n$ sudo dnf install libguestfs-tools\r\n$ sudo dnf install libvirt-python\r\n$ sudo systemctl enable libvirtd\r\n$ sudo systemctl start libvirtd\r\n$ systemctl status libvirtd\r\n$ lsmod | grep kvm\r\n$ sudo ls -l /var/lib/libvirt/images/\r\n$ sudo ls -l /var/lib/libvirt/iso\r\n$ rpm -qa | grep bridge-utils\r\n$ sudo yum install bridge-utils\r\n$ ip a\r\n$ brctl show\r\n$ systemctl enable --now libvirtd\r\n$ nmcli connection add type bridge autoconnect yes con-name br0 ifname br0\r\n$ sudo su\r\n# nmcli connection modify br0 ipv4.addresses 10.0.0.30/24 ipv4.method manual\r\n# nmcli connection modify br0 ipv4.gateway 10.0.0.1\r\n# nmcli connection modify br0 ipv4.dns 10.0.0.10\r\n# nmcli connection modify br0 ipv4.dns-search srv.world\r\n# nmcli connection up enp0s21f0u1u4\r\n# nmcli connection del enp0s21f0u1u4\r\n# nmcli device\r\n# nmcli connection add type bridge-slave autoconnect yes con-name enp0s21f0u1u4 ifname enp0s21f0u1u4 master br0\r\n# nmcli device\r\n# reboot\r\n# ip addr\r\n# virt-install \\\r\n--name ubuntu22.04 \\\r\n--ram 2048 \\\r\n--disk path=/var/lib/libvirt/images/ubuntu22.04.img,size=50 \\\r\n--vcpus 2 \\\r\n--os-variant Ubuntu \\\r\n--network bridge=br0 \\\r\n--graphics none \\\r\n--console pty,target_type=serial \\\r\n--location /var/lib/libvirt/iso/Ubuntu.iso \\\r\n--extra-args 'console=ttyS0,115200n8'\r\n$ sudo virsh list --all\r\n$ sudo virsh start ubuntu22.04\r\n$ ssh -X tuser@IP\r\nDecision:\r\n$ sudo apt update\r\n$ sudo apt install apache2\r\n$ sudo ufw app list\r\nAvailable applications:\r\n  Apache\r\n  Apache Full\r\n  Apache Secure\r\n  CUPS\r\n  OpenSSH\r\n$ sudo ufw enable\r\n$ sudo ufw allow in \"Apache\"\r\n$ sudo ufw allow in \"OpenSSH\"\r\n$ sudo ufw status\r\nStatus: active\r\nTo                         Action      From\r\n--                         ------      ----\r\nApache                     ALLOW       Anywhere                  \r\nApache Full                ALLOW       Anywhere                  \r\nOpenSSH                    ALLOW       Anywhere                  \r\nApache (v6)                ALLOW       Anywhere (v6)             \r\nApache Full (v6)           ALLOW       Anywhere (v6)             \r\nOpenSSH (v6)               ALLOW       Anywhere (v6)\r\n$ firefox\r\nupdate.go:85: cannot change mount namespace according to change mount (/var/lib/snapd/hostfs/usr/share/gimp/2.0/help /usr/share/gimp/2.0/help none bind,ro 0 0): cannot open directory \"/var/lib\": permission denied\r\nupdate.go:85: cannot change mount namespace according to change mount (/var/lib/snapd/hostfs/usr/share/xubuntu-docs /usr/share/xubuntu-docs none bind,ro 0 0): cannot open directory \"/var/lib\": permission denied\r\nX11 connection rejected because of wrong authentication.\r\nX11 connection rejected because of wrong authentication.\r\nX11 connection rejected because of wrong authentication.\r\nX11 connection rejected because of wrong authentication.\r\nX11 connection rejected because of wrong authentication.\r\nX11 connection rejected because of wrong authentication.\r\nError: cannot open display: localhost:10.0\r\nDecision:\r\n$ wget https://dl.google.com/linux/direct/google-chrome-stable_current_amd64.deb\r\n$ sudo dpkg -i --force-depends google-chrome-stable_current_amd64.deb\r\n$ google-chrome http://127.0.0.1\r\nDecision:\r\n$ sudo apt install mysql-server\r\n$ sudo mysql\r\nmysql> ALTER USER 'root'@'localhost' IDENTIFIED WITH mysql_native_password BY 'tpassword';\r\nmysql> exit\r\n$ sudo mysql_secure_installation\r\n$ sudo mysql\r\nERROR 1045 (28000): Access denied for user 'root'@'localhost' (using password: NO)\r\n$ sudo mysql -u root -p\r\nmysql> exit\r\nDecision:\r\n$ sudo apt install php libapache2-mod-php php-mysql\r\n$ php -v\r\n$ cat /etc/php/8.1/apache2/php.ini | grep upload_max_filesize\r\nupload_max_filesize = 2M\r\n$ cat /etc/php/8.1/apache2/php.ini | grep post_max_size\r\npost_max_size = 8M\r\n$ cat /etc/php/8.1/apache2/php.ini | grep memory_limit\r\nmemory_limit = 128M\r\n$ cat /etc/php/8.1/apache2/php.ini | grep max_execution_time\r\nmax_execution_time = 30\r\n$ cat /etc/php/8.1/apache2/php.ini | grep max_input_vars\r\n;max_input_vars = 1000\r\n$ cat /etc/php/8.1/apache2/php.ini | grep max_input_time\r\n; max_input_time\r\nmax_input_time = 60\r\n$ sudo vim /etc/php/8.1/apache2/php.ini\r\n$ cat /etc/php/8.1/apache2/php.ini | grep upload_max_filesize\r\nupload_max_filesize = 32M\r\n$ cat /etc/php/8.1/apache2/php.ini | grep post_max_size\r\npost_max_size = 48M\r\n$ cat /etc/php/8.1/apache2/php.ini | grep memory_limit\r\nmemory_limit = 256M\r\n$ cat /etc/php/8.1/apache2/php.ini | grep max_execution_time\r\nmax_execution_time = 600\r\n$ cat /etc/php/8.1/apache2/php.ini | grep max_input_vars\r\nmax_input_vars = 3000\r\n$ cat /etc/php/8.1/apache2/php.ini | grep max_input_time\r\n; max_input_time\r\nmax_input_time = 1000\r\n$ sudo service apache2 restart\r\nDecision:\r\n$ sudo mkdir /var/www/tdomain\r\n$ sudo chown -R $USER:$USER /var/www/tdomain\r\n$ sudo vim /etc/apache2/sites-available/tdomain.conf\r\n$ cat /etc/apache2/sites-available/tdomain.conf\r\n<VirtualHost *:80>\r\n    ServerName tdomain\r\n    ServerAlias www.tdomain\r\n    ServerAdmin webmaster@localhost\r\n    DocumentRoot /var/www/tdomain\r\n    ErrorLog ${APACHE_LOG_DIR}/error.log\r\n    CustomLog ${APACHE_LOG_DIR}/access.log combined\r\n</VirtualHost>\r\n$ sudo a2ensite tdomain\r\n$ sudo a2dissite 000-default\r\n$ sudo apache2ctl configtest\r\n$ sudo systemctl reload apache2\r\n$ vim /var/www/tdomain/index.html\r\n$ cat /var/www/tdomain/index.html\r\n<html>\r\n  <head>\r\n    <title>tdomain website</title>\r\n  </head>\r\n  <body>\r\n    <h1>Hello World!</h1>\r\n    <p>This is the landing page of <strong>tdomain</strong>.</p>\r\n  </body>\r\n</html>\r\n$ google-chrome http://127.0.0.1\r\nDecision:\r\n$ cat /etc/apache2/mods-enabled/dir.conf\r\n<IfModule mod_dir.c>\r\n    DirectoryIndex index.html index.cgi index.pl index.php index.xhtml index.htm\r\n</IfModule>\r\n# vim: syntax=apache ts=4 sw=4 sts=4 sr noet\r\n$ sudo vim /etc/apache2/mods-enabled/dir.conf\r\n$ cat /etc/apache2/mods-enabled/dir.conf\r\n<IfModule mod_dir.c>\r\n    DirectoryIndex index.php index.html index.cgi index.pl index.php index.xhtml index.htm\r\n</IfModule>\r\n# vim: syntax=apache ts=4 sw=4 sts=4 sr noet\r\n$ sudo systemctl reload apache2\r\n$ vim /var/www/tdomain/info.php\r\n$ cat /var/www/tdomain/info.php\r\n<?php\r\nphpinfo();\r\n$ google-chrome http://127.0.0.1/info.php\r\n$ sudo rm /var/www/tdomain/info.php\r\n$ sudo mysql -u root -p\r\nmysql> create database tbase;\r\nmysql> CREATE USER 'tuser'@'%' IDENTIFIED BY 'tpassword';\r\nmysql> GRANT ALL ON tbase.* TO 'tuser'@'%';\r\nmysql> exit\r\n$ mysql -u tuser -p\r\nmysql> show databases;\r\n+--------------------+\r\n| Database           |\r\n+--------------------+\r\n| information_schema |\r\n| performance_schema |\r\n| tbase              |\r\n+--------------------+\r\n3 rows in set (0.07 sec)\r\nmysql> create table tbase.ttable1\r\n    (ttable1_id INT PRIMARY KEY AUTO_INCREMENT,\r\n    content VARCHAR(255));\r\nCREATE TABLE tbase.ttable1\r\n    (ttable1_id INT PRIMARY KEY AUTO_INCREMENT,\r\n    column1 VARCHAR(255),\r\n    column2 VARCHAR(255),\r\n    column3 VARCHAR(255),\r\n    column4 VARCHAR(255),\r\n    column5 Date,\r\n    column6 Date);\r\nmysql> INSERT INTO tbase.ttable1\r\n    (column1, column2)\r\nVALUES\r\n    (\"text1\",\"text2\"),\r\n    (\"text3\",\"text4\"),\r\n    (\"text5\",\"text6\"),\r\n    (\"text7\",\"text8\");\r\nmysql> select * from tbase.ttable1;\r\n+------------+---------+---------+---------+---------+---------+---------+\r\n| ttable1_id | column1 | column2 | column3 | column4 | column5 | column6 |\r\n+------------+---------+---------+---------+---------+---------+---------+\r\n|          1 | text1   | text2   | NULL    | NULL    | NULL    | NULL    |\r\n|          2 | text3   | text4   | NULL    | NULL    | NULL    | NULL    |\r\n|          3 | text5   | text6   | NULL    | NULL    | NULL    | NULL    |\r\n|          4 | text7   | text8   | NULL    | NULL    | NULL    | NULL    |\r\n+------------+---------+---------+---------+---------+---------+---------+\r\n4 rows in set (0.00 sec)\r\nmysql> CREATE TABLE tbase.ttable2\r\n    (ttable2_id INT PRIMARY KEY AUTO_INCREMENT,\r\n    columnId INT,\r\n    column1 VARCHAR(500),\r\n    FOREIGN KEY (columnId) REFERENCES tbase.ttable1 (ttable1_id));\r\nmysql> INSERT INTO tbase.ttable2\r\n    (columnId, column1)\r\nVALUES\r\n    (1, \"text9\"),\r\n    (1, \"text10\"),\r\n    (2, \"text11\"),\r\n    (3, \"text12\"),\r\n    (4, \"text13\");\r\nmysql> select * from tbase.ttable2;\r\n+------------+----------+---------+\r\n| ttable2_id | columnId | column1 |\r\n+------------+----------+---------+\r\n|          1 |        1 | text9   |\r\n|          2 |        1 | text10  |\r\n|          3 |        2 | text11  |\r\n|          4 |        3 | text12  |\r\n|          5 |        4 | text13  |\r\n+------------+----------+---------+\r\n5 rows in set (0.00 sec)\r\nmysql> select * from tbase.ttable2\r\n    inner join tbase.ttable1\r\n    on ttable1.ttable1_id = ttable2.columnId;\r\n+------------+----------+---------+------------+---------+---------+---------+---------+---------+---------+\r\n| ttable2_id | columnId | column1 | ttable1_id | column1 | column2 | column3 | column4 | column5 | column6 |\r\n+------------+----------+---------+------------+---------+---------+---------+---------+---------+---------+\r\n|          1 |        1 | text9   |          1 | text1   | text2   | NULL    | NULL    | NULL    | NULL    |\r\n|          2 |        1 | text10  |          1 | text1   | text2   | NULL    | NULL    | NULL    | NULL    |\r\n|          3 |        2 | text11  |          2 | text3   | text4   | NULL    | NULL    | NULL    | NULL    |\r\n|          4 |        3 | text12  |          3 | text5   | text6   | NULL    | NULL    | NULL    | NULL    |\r\n|          5 |        4 | text13  |          4 | text7   | text8   | NULL    | NULL    | NULL    | NULL    |\r\n+------------+----------+---------+------------+---------+---------+---------+---------+---------+---------+\r\n5 rows in set (0.00 sec)\r\nmysql> exit\r\n$ vim /var/www/tdomain/index.php\r\n$ cat /var/www/tdomain/index.php\r\n<?php\r\n$user = \"tuser\";\r\n$password = \"tpassword\";\r\n$database = \"tbase\";\r\n$table1 = \"ttable1\";\r\n$table2 = \"ttable2\";\r\ntry {\r\n    $db = new PDO(\"mysql:host=localhost;dbname=$database\", $user, $password);\r\n    $query = $db->query(\"\r\n        select * from $database.$table2\r\n        inner join $database.$table1\r\n        on $table1.experience_id=$table2.experienceId;\r\n    \");\r\n    foreach($query as $row) {\r\n        echo '\r\n        <li><strong>\r\n        ' . $row['column1'] . '\r\n        -\r\n        ' . $row['column2'] . '\r\n        :</strong>\r\n        ' . $row['column3'] . '\r\n        ;\r\n        ' . $row['column4'] . '\r\n        ;\r\n        ' . $row['column5'] . '\r\n        ;\r\n        ' . $row['column6'] . '\r\n        </li>\r\n        ';\r\n    }\r\n} catch (PDOException $e) {\r\n    print \"Error!: \" . $e->getMessage() . \"<br/>\";\r\n    die();\r\n}\r\n$ google-chrome http://127.0.0.1/index.php\r\nDecision:\r\n$ sudo apt update\r\n$ sudo apt install phpmyadmin php-mbstring php-zip php-gd php-json php-curl\r\n$ sudo apt install php8.1-fpm php8.1 libapache2-mod-php8.1 php8.1-common php8.1-mysql php8.1-xml php8.1-xmlrpc php8.1-imagick php8.1-cli php8.1-imap php8.1-opcache php8.1-soap php8.1-intl php8.1-bcmath unzip\r\n...\r\ngranting access to database phpmyadmin for phpmyadmin@localhost: failed.\r\nerror encountered creating user:\r\nmysql said: ERROR 1819 (HY000) at line 1: Your password does not satisfy the cur\r\nrent policy requirements\r\ndbconfig-common: phpmyadmin configure: aborted.\r\ndbconfig-common: flushing administrative password\r\ndpkg: error processing package phpmyadmin (--configure):\r\n installed phpmyadmin package post-installation script subprocess returned error\r\n exit status 1\r\nProcessing triggers for libapache2-mod-php8.1 (8.1.2-1ubuntu2.14) ...\r\n...\r\nErrors were encountered while processing:\r\n phpmyadmin\r\nE: Sub-process /usr/bin/dpkg returned an error code (1)\r\n$ mysql -u root -p\r\nmysql> UNINSTALL COMPONENT \"file://component_validate_password\";\r\nmysql> exit\r\n$ sudo apt install phpmyadmin\r\n...\r\ngranting access to database phpmyadmin for phpmyadmin@localhost: success.\r\nverifying access for phpmyadmin@localhost: success.\r\ncreating database phpmyadmin: success.\r\nverifying database phpmyadmin exists: success.\r\npopulating database via sql...  done.\r\ndbconfig-common: flushing administrative password\r\n$ mysql -u root -p\r\nmysql> INSTALL COMPONENT \"file://component_validate_password\";\r\nmysql> exit\r\n$ sudo phpenmod mbstring\r\n$ sudo systemctl restart apache2\r\n$ mysql -u root -p\r\nmysql> SELECT user,authentication_string,plugin,host FROM mysql.user;\r\nmysql> exit\r\n$ sudo cp /etc/phpmyadmin/apache.conf /etc/apache2/conf-available/phpmyadmin.conf\r\n$ sudo a2enconf phpmyadmin.conf\r\n$ systemctl reload apache2\r\n$ google-chrome http://127.0.0.1/phpmyadmin &\r\nDecision:\r\n$ wget -qO - https://download.sublimetext.com/sublimehq-pub.gpg | sudo tee /etc/apt/trusted.gpg.d/sublimehq-pub.asc\r\n$ sudo apt update\r\n$ sudo apt-get install apt-transport-https\r\n$ echo \"deb https://download.sublimetext.com/ apt/stable/\" | sudo tee /etc/apt/sources.list.d/sublime-text.list\r\n$ sudo apt update\r\n$ sudo apt install sublime-text\r\nDecision:\r\n$ exit\r\n# virsh shutdown ubuntu22.04\r\nSource:\r\nhttps://winitpro.ru/index.php/2020/02/10/virsh-upravlenie-virtualnymi-mashinami-kvm/\r\nhttps://winitpro.ru/index.php/2020/02/04/ustanovka-zapusk-kvm-v-linux-centos/\r\nhttps://www.server-world.info/en/note?os=CentOS_Stream_9&p=kvm&f=1\r\nhttps://www.server-world.info/en/note?os=CentOS_Stream_9&p=initial_conf&f=3\r\nhttps://www.server-world.info/en/note?os=CentOS_Stream_9&p=kvm&f=2\r\nhttps://www.digitalocean.com/community/tutorials/how-to-install-linux-apache-mysql-php-lamp-stack-on-ubuntu-22-04\r\nhttps://losst.pro/ustanovka-chrome-v-ubuntu-18-04?ysclid=lmdflkvc3v463974954\r\nhttps://qna.habr.com/q/439469?ysclid=lmdgkb49q827401606\r\nhttps://metanit.com/sql/mysql/2.5.php\r\nhttps://metanit.com/sql/mysql/5.2.php\r\nhttps://www.digitalocean.com/community/tutorials/how-to-install-and-secure-phpmyadmin-on-ubuntu-20-04\r\nhttps://serverspace.ru/support/help/osnovnye-komandy-ufw/\r\nhttps://www.tutsmake.com/how-to-install-lamp-apache-mysql-php-in-ubuntu-22-04/\r\nhttps://www.php.net/manual/ru/faq.html.php\r\nhttps://www.8host.com/blog/kak-rabotayut-stroki-v-php/", "image": "uploads/2024/02/06/test.jpg", "url": "https://vk.com", "ordinal": 1}}, {"model": "portfolio.portfolio", "pk": 2, "fields": {"title": "тест", "description": "тест", "image": "uploads/2024/02/10/test_Q7c03Ah.jpg", "url": "http://127.0.0.1:8000/portfolio/", "ordinal": 2}}, {"model": "portfolio.category", "pk": 4, "fields": {"name": "Engineer", "ordinal": 1}}, {"model": "portfolio.category", "pk": 5, "fields": {"name": "Developer", "ordinal": 2}}]